nepali/__init__.py
nepali/char.py
nepali/constants.py
nepali/date_converter.py
nepali/exceptions.py
nepali/phone_number.py
nepali/timezone.py
nepali/utils.py
nepali/datetime/__init__.py
nepali/datetime/_datetime.py
nepali/datetime/_formatter.py
nepali/datetime/_humanize.py
nepali/datetime/_nepalimonth.py
nepali/datetime/_nepaliweek.py
nepali/datetime/utils.py
nepali/datetime/parser/__init__.py
nepali/datetime/parser/_parser.py
nepali/datetime/parser/validators.py
nepali/locations/__init__.py
nepali/locations/_data.py
nepali/locations/_locations.py
nepali/locations/models.py
nepali/locations/utils.py
nepali/number/__init__.py
nepali/number/_nepalinumber.py
nepali/number/_number.py
nepali/number/utils.py
nepali/templatetags/__init__.py
nepali/templatetags/nepalidatetime.py
nepali/templatetags/nepalinumber.py
nepali/tests/__init__.py
nepali/tests/test_date_converter.py
nepali/tests/test_datetime.py
nepali/tests/test_humanize.py
nepali/tests/test_locations.py
nepali/tests/test_nepalimonth.py
nepali/tests/test_nepaliweek.py
nepali/tests/test_number.py
nepali/tests/test_parser.py
nepali/tests/test_phone_number.py
nepali/tests/test_timezone.py
nepali-1.1.3.dist-info/licenses/LICENSE
nepali-1.1.3.dist-info/METADATA
nepali-1.1.3.dist-info/WHEEL
nepali-1.1.3.dist-info/top_level.txt
nepali-1.1.3.dist-info/RECORD
