Metadata-Version: 2.4
Name: nepali
Version: 1.1.3
Summary: nepalidatetime compatible with python's datetime feature. Converting nepali date to english, parsing nepali datetime, nepali timezone, and timedelta support in nepali datetime
Home-page: https://github.com/opensource-nepal/py-nepali
Author: opensource-nepal
Author-email: aj3sshh@gmail.com, sugatbajracharya49@gmail.com
License: MIT
Project-URL: Source, https://github.com/opensource-nepal/py-nepali
Project-URL: Changelog, https://github.com/opensource-nepal/py-nepali/blob/main/CHANGELOG.md
Keywords: nepali date conversion,convert date,nepali date time,python convert date,parse nepali date time
Classifier: Programming Language :: Python :: 3
Classifier: License :: OSI Approved :: MIT License
Classifier: Operating System :: OS Independent
License-File: LICENSE
Dynamic: author
Dynamic: author-email
Dynamic: classifier
Dynamic: description
Dynamic: description-content-type
Dynamic: home-page
Dynamic: keywords
Dynamic: license
Dynamic: license-file
Dynamic: project-url
Dynamic: summary
